pyDMNrules/DMNrules.py
pyDMNrules/__init__.py
pyDMNrules-1.4.4.dist-info/LICENSE
pyDMNrules-1.4.4.dist-info/METADATA
pyDMNrules-1.4.4.dist-info/WHEEL
pyDMNrules-1.4.4.dist-info/top_level.txt
pyDMNrules-1.4.4.dist-info/RECORD
