Metadata-Version: 2.1
Name: pyDMNrules
Version: 1.4.4
Summary: An implementation of DMN in Python. DMN rules are read from an Excel workbook
Home-page: https://github.com/russellmcdonell/pyDMNrules
Author: Russell McDonell
Author-email: russell.mcdonell@c-cost.com
Classifier: Programming Language :: Python :: 3
Classifier: License :: OSI Approved :: GNU General Public License v3 (GPLv3)
Classifier: Operating System :: OS Independent
Requires-Python: >=3.6
License-File: LICENSE
Requires-Dist: datetime
Requires-Dist: pySFeel
Requires-Dist: openpyxl
Requires-Dist: pandas
